opusdsd/__init__.py
opusdsd/bibtex.py
opusdsd/constants.py
opusdsd/cryodrgn_logo.png
opusdsd/protocols.conf
opusdsd/utils.py
opusdsd/viewers.py
opusdsd/protocols/__init__.py
opusdsd/protocols/protocol_analyze.py
opusdsd/protocols/protocol_training.py
opusdsd/tests/__init__.py
opusdsd/tests/test_opusdsd.py
scipion_em_opusdsd-3.3.0.dist-info/LICENSE
scipion_em_opusdsd-3.3.0.dist-info/METADATA
scipion_em_opusdsd-3.3.0.dist-info/WHEEL
scipion_em_opusdsd-3.3.0.dist-info/entry_points.txt
scipion_em_opusdsd-3.3.0.dist-info/top_level.txt
scipion_em_opusdsd-3.3.0.dist-info/RECORD
