Metadata-Version: 2.1
Name: scipion-em-opusdsd
Version: 3.3.0
Summary: Plugin to use Opusdsd programs within the Scipion framework
Author-email: James Krieger <jamesmkrieger@gmail.com>, Eduardo García <edugarde01@gmail.com>
License: GNU General Public License v3 (GPLv3)
Project-URL: Homepage, https://github.com/scipion-em/scipion-em-opusdsd
Project-URL: Repository, https://github.com/scipion-em/scipion-em-opusdsd
Project-URL: Issues, https://github.com/scipion-em/scipion-em-opusdsd/issues
Keywords: scipion,electron-microscopy,cryo-em,structural-biology,image-processing,scipion-3.0,opusdsd
Requires-Python: >=3.8
License-File: LICENSE
Requires-Dist: scipion-em
Requires-Dist: scipion-pyworkflow
